aliyunsdkcloudfw/__init__.py
aliyunsdkcloudfw/endpoint.py
aliyunsdkcloudfw/request/__init__.py
aliyunsdkcloudfw/request/v20171207/AddAddressBookRequest.py
aliyunsdkcloudfw/request/v20171207/AddControlPolicyRequest.py
aliyunsdkcloudfw/request/v20171207/AddInstanceMembersRequest.py
aliyunsdkcloudfw/request/v20171207/BatchCopyVpcFirewallControlPolicyRequest.py
aliyunsdkcloudfw/request/v20171207/CreateNatFirewallControlPolicyRequest.py
aliyunsdkcloudfw/request/v20171207/CreateTrFirewallV2Request.py
aliyunsdkcloudfw/request/v20171207/CreateTrFirewallV2RoutePolicyRequest.py
aliyunsdkcloudfw/request/v20171207/CreateVpcFirewallCenConfigureRequest.py
aliyunsdkcloudfw/request/v20171207/CreateVpcFirewallConfigureRequest.py
aliyunsdkcloudfw/request/v20171207/CreateVpcFirewallControlPolicyRequest.py
aliyunsdkcloudfw/request/v20171207/DeleteAddressBookRequest.py
aliyunsdkcloudfw/request/v20171207/DeleteControlPolicyRequest.py
aliyunsdkcloudfw/request/v20171207/DeleteFirewallV2RoutePoliciesRequest.py
aliyunsdkcloudfw/request/v20171207/DeleteInstanceMembersRequest.py
aliyunsdkcloudfw/request/v20171207/DeleteNatFirewallControlPolicyRequest.py
aliyunsdkcloudfw/request/v20171207/DeleteTrFirewallV2Request.py
aliyunsdkcloudfw/request/v20171207/DeleteVpcFirewallCenConfigureRequest.py
aliyunsdkcloudfw/request/v20171207/DeleteVpcFirewallConfigureRequest.py
aliyunsdkcloudfw/request/v20171207/DeleteVpcFirewallControlPolicyRequest.py
aliyunsdkcloudfw/request/v20171207/DescribeAddressBookRequest.py
aliyunsdkcloudfw/request/v20171207/DescribeAssetListRequest.py
aliyunsdkcloudfw/request/v20171207/DescribeControlPolicyRequest.py
aliyunsdkcloudfw/request/v20171207/DescribeDefaultIPSConfigRequest.py
aliyunsdkcloudfw/request/v20171207/DescribeDomainResolveRequest.py
aliyunsdkcloudfw/request/v20171207/DescribeInstanceMembersRequest.py
aliyunsdkcloudfw/request/v20171207/DescribeInternetTrafficTrendRequest.py
aliyunsdkcloudfw/request/v20171207/DescribeInvadeEventListRequest.py
aliyun_python_sdk_cloudfw-1.0.0.dist-info/LICENSE
aliyun_python_sdk_cloudfw-1.0.0.dist-info/METADATA
aliyun_python_sdk_cloudfw-1.0.0.dist-info/WHEEL
aliyun_python_sdk_cloudfw-1.0.0.dist-info/top_level.txt
aliyun_python_sdk_cloudfw-1.0.0.dist-info/RECORD
